setup.py
macrofi/__init__.py
macrofi.egg-info/PKG-INFO
macrofi.egg-info/SOURCES.txt
macrofi.egg-info/dependency_links.txt
macrofi.egg-info/not-zip-safe
macrofi.egg-info/requires.txt
macrofi.egg-info/top_level.txt
macrofi/data_agent/__init__.py
macrofi/data_agent/daily_emotion_agent.py
macrofi/data_agent/daily_macro_agent.py
macrofi/data_agent/monthly_macro_agent.py
macrofi/data_agent/validation_agent.py
macrofi/evaluation/__init__.py
macrofi/event_selection/__init__.py
macrofi/event_selection/common.py
macrofi/event_selection/event.py
macrofi/event_selection/event_agent.py
macrofi/event_selection/event_optimize.py
macrofi/event_selection/factor_event.py
macrofi/event_selection/factor_validator.py
macrofi/event_selection/fibacktest.py
macrofi/event_selection/ga.py
macrofi/event_selection/performance.py
macrofi/feature_engineering/__init__.py
macrofi/feature_selection/__init__.py
macrofi/gui/__init__.py
macrofi/gui/firstPyQt5.py
macrofi/gui/matplot.py
macrofi/helper/__init__.py
macrofi/helper/common.py
macrofi/models/__init__.py
macrofi/models/non_regression_simple.py
macrofi/models/zy_model.py
macrofi/pipeline_lib/__init__.py