Metadata-Version: 1.0
Name: macrofi
Version: 0.2.1
Summary: PyMacroFI Platform
Home-page: http://wangluzhou.com
Author: wangluzhou
Author-email: wangluzhou@aliyun.com
License: MIT
Platform: UNKNOWN
